django_ses_plus/__init__.py
django_ses_plus/admin.py
django_ses_plus/apps.py
django_ses_plus/backends.py
django_ses_plus/models.py
django_ses_plus/settings.py
django_ses_plus/tasks.py
django_ses_plus/utils.py
django_ses_plus/migrations/0001_initial.py
django_ses_plus/migrations/__init__.py
django_ses_plus-1.0.0.dist-info/LICENSE
django_ses_plus-1.0.0.dist-info/METADATA
django_ses_plus-1.0.0.dist-info/WHEEL
django_ses_plus-1.0.0.dist-info/top_level.txt
django_ses_plus-1.0.0.dist-info/RECORD
