Metadata-Version: 2.1
Name: django-ses-plus
Version: 1.0.0
Summary: It's a Django module to store and send email with AWS SES.
Home-page: https://github.com/Hipo/django-ses-plus
Author: hipo
Author-email: pypi@hipolabs.com
License: Apache-2.0
Platform: UNKNOWN
Classifier: Environment :: Web Environment
Classifier: Framework :: Django :: 3.2
Classifier: Framework :: Django :: 4.0
Classifier: Framework :: Django :: 4.1
Classifier: Intended Audience :: Developers
Classifier: Operating System :: OS Independent
Classifier: License :: OSI Approved :: BSD License
Classifier: Programming Language :: Python
Classifier: Programming Language :: Python :: 3
Classifier: Programming Language :: Python :: 3.6
Classifier: Programming Language :: Python :: 3.7
Classifier: Programming Language :: Python :: 3.8
Classifier: Programming Language :: Python :: 3.9
Classifier: Programming Language :: Python :: 3.10
Classifier: Topic :: Internet :: WWW/HTTP
Classifier: Topic :: Internet :: WWW/HTTP :: Dynamic Content
Requires-Python: >=3.6
License-File: LICENSE
Requires-Dist: Django (>=3.2)
Requires-Dist: django-ses (>=2.1.1)
Requires-Dist: celery (>=4)
